pymagnet/__init__.py
pymagnet/forces/__init__.py
pymagnet/forces/_cylinder_force.py
pymagnet/forces/_mesh_force.py
pymagnet/forces/_prism_force.py
pymagnet/forces/_sphere_force.py
pymagnet/magnets/__init__.py
pymagnet/magnets/_magnet1D.py
pymagnet/magnets/_magnet2D.py
pymagnet/magnets/_magnet3D.py
pymagnet/magnets/_magnet_base.py
pymagnet/magnets/_polygon2D.py
pymagnet/magnets/_polygon3D.py
pymagnet/plots/__init__.py
pymagnet/plots/_plot1D.py
pymagnet/plots/_plot2D.py
pymagnet/plots/_plotly2D.py
pymagnet/plots/_plotly3D.py
pymagnet/utils/__init__.py
pymagnet/utils/_assemblies2D.py
pymagnet/utils/_conversions.py
pymagnet/utils/_fit.py
pymagnet/utils/_point_structs.py
pymagnet/utils/_quaternion.py
pymagnet/utils/_routines2D.py
pymagnet/utils/_routines3D.py
pymagnet/utils/_trigonometry3D.py
pymagnet/utils/_vector_structs.py
pymagnet/utils/global_const.py
pymagnet-0.4.1.dist-info/LICENSE
pymagnet-0.4.1.dist-info/WHEEL
pymagnet-0.4.1.dist-info/METADATA
pymagnet-0.4.1.dist-info/RECORD
