Metadata-Version: 2.1
Name: pymagnet
Version: 0.4.1
Summary: User Friendly Magnetic Field Calculations
Home-page: https://www.applied-magnetism.com
License: MPL-2.0
Keywords: magnetism,magnetic fields
Author: Peter Dunne
Author-email: peter.dunne@applied-magnetism.com
Requires-Python: >=3.7,<3.10
Classifier: Development Status :: 3 - Alpha
Classifier: Intended Audience :: Science/Research
Classifier: License :: OSI Approved
Classifier: License :: OSI Approved :: Mozilla Public License 2.0 (MPL 2.0)
Classifier: Programming Language :: Python :: 3
Classifier: Programming Language :: Python :: 3 :: Only
Classifier: Programming Language :: Python :: 3.10
Classifier: Programming Language :: Python :: 3.7
Classifier: Programming Language :: Python :: 3.8
Classifier: Programming Language :: Python :: 3.9
Classifier: Topic :: Scientific/Engineering
Requires-Dist: matplotlib (>=3.5.0,<4.0.0)
Requires-Dist: numba (>=0.55.1,<0.56.0)
Requires-Dist: numpy (>=1.21,<2.0)
Requires-Dist: numpy-stl (>=2.16.3,<3.0.0)
Requires-Dist: plotly (>=5.4.0,<6.0.0)
Project-URL: Documentation, https://pdunne.github.io/pymagnet/
Project-URL: Repository, https://github.com/pdunne/pymagnet
